LICENSE
terramagic.py
terramagic-0.3.0.dist-info/LICENSE
terramagic-0.3.0.dist-info/METADATA
terramagic-0.3.0.dist-info/WHEEL
terramagic-0.3.0.dist-info/entry_points.txt
terramagic-0.3.0.dist-info/RECORD
