Metadata-Version: 2.1
Name: terramagic
Version: 0.3.0
Summary: A automate tool for terraform projects
Home-page: https://github.com/miltlima/terramagic
License: MIT
Keywords: terraform,terramagic,python
Author: Milton Jesus
Author-email: milton.lima@outlook.com
Requires-Python: >=3.9,<4.0
Classifier: Environment :: Console
Classifier: License :: OSI Approved :: MIT License
Classifier: Operating System :: OS Independent
Classifier: Programming Language :: Python :: 3
Classifier: Programming Language :: Python :: 3.9
Classifier: Programming Language :: Python :: 3.10
Classifier: Programming Language :: Python :: 3.11
Classifier: Topic :: Software Development :: Documentation
Requires-Dist: click (>=8.0.3,<9.0.0)
Requires-Dist: python-hcl2 (>=4.3.0,<5.0.0)
Requires-Dist: termcolor (>=1.1.0,<2.0.0)
Project-URL: Repository, https://github.com/miltlima/terramagic
